{
	"description": "项目配置文件",
	"packOptions": {
		"ignore": []
	},
	"setting": {
		"urlCheck": false,
		"es6": false,
		"postcss": true,
		"minified": true,
		"newFeature": true,
		"autoAudits": false,
		"checkInvalidKey": true
	},
	"compileType": "miniprogram",
	"libVersion": "2.9.1",
	"appid": "wxbdbe24d4215ec5b5",
	"projectname": "miniprogram-test-1",
	"debugOptions": {
		"hidedInDevtools": []
	},
	"isGameTourist": false,
	"simulatorType": "wechat",
	"simulatorPluginLibVersion": {},
	"condition": {
		"search": {
			"current": -1,
			"list": []
		},
		"conversation": {
			"current": -1,
			"list": []
		},
		"plugin": {
			"current": -1,
			"list": []
		},
		"game": {
			"currentL": -1,
			"list": []
		},
		"miniprogram": {
			"current": 2,
			"list": [
				{
					"id": -1,
					"name": "0",
					"pathName": "pages/read/read",
					"query": "",
					"scene": null
				},
				{
					"id": -1,
					"name": "1",
					"pathName": "pages/read-detail/read-detail",
					"query": "",
					"scene": null
				},
				{
					"id": -1,
					"name": "2",
					"pathName": "pages/movie/movie",
					"scene": null
				}
			]
		}
	}
}